kryptal/__init__.py
kryptal/gui/Application.py
kryptal/gui/MainWindow.py
kryptal/gui/TaskManager.py
kryptal/gui/TrayIcon.py
kryptal/gui/__init__.py
kryptal/gui/__main__.py
kryptal/gui/mainwindow.ui
kryptal/gui/test_Application.py
kryptal/gui/test_MainWindow.py
kryptal/gui/test_TaskManager.py
kryptal/gui/test_main.py
kryptal/gui/controller/CreateDirectoryYesNoController.py
kryptal/gui/controller/CreateFilesystemController.py
kryptal/gui/controller/MountFilesystemController.py
kryptal/gui/controller/RemoveFilesystemController.py
kryptal/gui/controller/__init__.py
kryptal/gui/controller/test_CreateDirectoryYesNoController.py
kryptal/gui/controller/test_CreateFilesystemController.py
kryptal/gui/controller/test_CreateFilesystem_Integration.py
kryptal/gui/view/__init__.py
kryptal/gui/view/dialogs/AboutDialog.py
kryptal/gui/view/dialogs/CreateFilesystemDialog.py
kryptal/gui/view/dialogs/__init__.py
kryptal/gui/view/dialogs/about.ui
kryptal/gui/view/dialogs/createfilesystemdialog.ui
kryptal/gui/view/dialogs/test_AboutDialog.py
kryptal/gui/view/dialogs/test_CreateFilesystemDialog.py
kryptal/gui/view/icons/Icons.py
kryptal/gui/view/icons/__init__.py
kryptal/gui/view/icons/drive-harddisk.svg
kryptal/gui/view/icons/gear.svg
kryptal/gui/view/icons/logo.png
kryptal/gui/view/icons/sources.txt
kryptal/gui/view/icons/spinner.gif
kryptal/gui/view/utils/AsyncQDialog.py
kryptal/gui/view/utils/AsyncSlot.py
kryptal/gui/view/utils/DirCompleter.py
kryptal/gui/view/utils/PasswordsMatchPolicy.py
kryptal/gui/view/utils/__init__.py
kryptal/gui/view/utils/test_PasswordsMatchPolicy.py
kryptal/gui/view/widgets/DirSelector.py
kryptal/gui/view/widgets/FileSystemList.py
kryptal/gui/view/widgets/FileSystemListItem.py
kryptal/gui/view/widgets/SpinnerButton.py
kryptal/gui/view/widgets/SpinnerLabel.py
kryptal/gui/view/widgets/__init__.py
kryptal/gui/view/widgets/dirselector.ui
kryptal/gui/view/widgets/filesystemlistitem.ui
kryptal/gui/view/widgets/test_DirSelector.py
kryptal-0.1.18.dist-info/LICENSE
kryptal-0.1.18.dist-info/METADATA
kryptal-0.1.18.dist-info/WHEEL
kryptal-0.1.18.dist-info/entry_points.txt
kryptal-0.1.18.dist-info/top_level.txt
kryptal-0.1.18.dist-info/RECORD
