Metadata-Version: 2.1
Name: kryptal
Version: 0.1.18
Summary: Manage encrypted file systems, for example to encrypt your cloud storage.
Home-page: https://github.com/cryfs/kryptal
Author: Sebastian Messmer
Author-email: messmer@cryfs.org
License: GPLv3
Platform: UNKNOWN
Classifier: Development Status :: 2 - Pre-Alpha
Classifier: Environment :: Console
Classifier: Environment :: X11 Applications
Classifier: Environment :: X11 Applications :: Qt
Classifier: Operating System :: MacOS
Classifier: Operating System :: POSIX
Classifier: Operating System :: POSIX :: Linux
Classifier: Intended Audience :: End Users/Desktop
Classifier: License :: OSI Approved :: GNU General Public License v3 or later (GPLv3+)
Classifier: Natural Language :: English
Classifier: Programming Language :: Python
Classifier: Programming Language :: Python :: 3 :: Only
Classifier: Topic :: Communications :: File Sharing
Classifier: Topic :: Security
Classifier: Topic :: Security :: Cryptography
Classifier: Topic :: System :: Filesystems
Classifier: Topic :: Utilities
Requires-Dist: PyQT5 (==5.15.1)
Requires-Dist: PyYAML (==5.3.1)
Requires-Dist: appdirs (==1.4.4)
Requires-Dist: asyncqt (==0.8.0)
Requires-Dist: mypy (==0.782)
Requires-Dist: typing-extensions (==3.7.4.3)
Requires-Dist: yapsy (==1.12.2)
Provides-Extra: test
Requires-Dist: coverage (==5.3) ; extra == 'test'
Requires-Dist: nose (==1.3.7) ; extra == 'test'
